pyduct/__init__.py
pyduct/_nbdev.py
pyduct/pipes.py
pyduct-0.0.1.dist-info/LICENSE
pyduct-0.0.1.dist-info/METADATA
pyduct-0.0.1.dist-info/WHEEL
pyduct-0.0.1.dist-info/top_level.txt
pyduct-0.0.1.dist-info/RECORD
