Metadata-Version: 2.1
Name: pyduct
Version: 0.0.1
Summary: A framework for building and running simple data engineering pipelines in Python.
Home-page: https://github.com/robtheoceanographer/pyduct/tree/master/
Author: Robert Johnson and Alexander Kozlov and Mohammadreza Khanarmuei
Author-email: robtheoceanographer@gmail.com
License: Apache Software License 2.0
Keywords: data pipeline framework template
Platform: UNKNOWN
Classifier: Development Status :: 3 - Alpha
Classifier: Intended Audience :: Developers
Classifier: Natural Language :: English
Classifier: Programming Language :: Python :: 3.6
Classifier: Programming Language :: Python :: 3.7
Classifier: Programming Language :: Python :: 3.8
Classifier: Programming Language :: Python :: 3.9
Classifier: Programming Language :: Python :: 3.10
Classifier: License :: OSI Approved :: Apache Software License
Requires-Python: >=3.6
License-File: LICENSE
Requires-Dist: pip
Requires-Dist: packaging
Provides-Extra: dev
